Workbook
Name AttrUnique: TypeSystem!$E$1
Name AttrQualifier: TypeSystem!$C$1
Name AttrLocLang: TypeSystem!$I$1
Name AttrLocalized: TypeSystem!$H$1
Name AttrTypeCode: TypeSystem!$F$1
Name AttrDisplayedNameRef: TypeSystem!$J$1
Name AttrName: TypeSystem!$D$1
Name TypeName: TypeSystem!$B$1
Name AttrTypeItemType: TypeSystem!$G$1
Name AttrOptional: TypeSystem!$E$1
Name TypeCode: TypeSystem!$A$1
Name HeaderTypeCode: HeaderPrompt!$A$1

Sheet TypeTemplate
A1: (Select Property)
A2: =IFERROR(VLOOKUP(A$1,HeaderPrompt!B:C,2,FALSE),"") | B2: =IFERROR(VLOOKUP(B$1,HeaderPrompt!B:C,2,FALSE),"") | C2: =IFERROR(VLOOKUP(C$1,HeaderPrompt!B:C,2,FALSE),"") | D2: =IFERROR(VLOOKUP(D$1,HeaderPrompt!B:C,2,FALSE),"") | E2: =IFERROR(VLOOKUP(E$1,HeaderPrompt!B:C,2,FALSE),"") | F2: =IFERROR(VLOOKUP(F$1,HeaderPrompt!B:C,2,FALSE),"") | G2: =IFERROR(VLOOKUP(G$1,HeaderPrompt!B:C,2,FALSE),"") | H2: =IFERROR(VLOOKUP(H$1,HeaderPrompt!B:C,2,FALSE),"") | ... KN2: =IFERROR(VLOOKUP(KN$1,HeaderPrompt!B:C,2,FALSE),"")

Sheet TypeSystem
A1: TypeCode | B1: TypeName | C1: AttrQualifier | D1: AttrName | E1: AttrOptional | F1: AttrTypeCode | G1: AttrTypeItemType | H1: AttrLocalized | I1: AttrLocLang | J1: AttrDisplayedName | K1: AttrUnique | L1: ReferenceFormat
A2: {Product} | B2: Product | C2: simpleBannerComponents | D2: Simple Banner Components | E2: true | F2: SimpleBannerComponentsForProductsimpleBannerComponentsColl | G2: Product | H2: false | J2: {Simple Banner Components+} | K2: false | L2: SimpleBannerComponent.uid:CatalogVersion.version:Catalog.id
A3: {Product} | B3: Product | C3: offlineDate | D3: Online to | E3: true | F3: java.util.Date | G3: Product | H3: false | J3: {Online to} | K3: false | L3: dd.MM.yyyy HH:mm:ss
A4: {Product} | B4: Product | C4: packagingSize | E4: true | F4: java.lang.String | G4: Product | H4: false | J4: {packagingSize} | K4: false
A5: {Product} | B5: Product | C5: comments | D5: Comments | E5: true | F5: CommentItemRelationcommentsColl | G5: Item | H5: false | J5: {Comments+} | K5: false | L5: Comment.code
A6: {Product} | B6: Product | C6: remarks | D6: Remarks | E6: true | F6: localized:java.lang.String | G6: Product | H6: true | I6: {en},{de},{ja},{zh} | J6: {Remarks[en]},{Remarks[de]},{Remarks[ja]},{Remarks[zh]} | K6: false
A7: {Product} | B7: Product | C7: productType | E7: true | F7: ProductType | G7: Product | H7: false | J7: {productType} | K7: false
A8: {Product} | B8: Product | C8: thumbnail | D8: Thumbnail | E8: true | F8: Media | G8: Product | H8: false | J8: {Thumbnail} | K8: false | L8: filePath:code:catalog:version:folder
A9: {Product} | B9: Product | C9: length | E9: true | F9: java.lang.String | G9: Product | H9: false | J9: {length} | K9: false
A10: {Product} | B10: Product | C10: linkComponents | D10: Link Components | E10: true | F10: CmsLinkComponentsForProductlinkComponentsColl | G10: Product | H10: false | J10: {Link Components+} | K10: false | L10: CMSLinkComponent.uid:CatalogVersion.version:Catalog.id
A11: {Product} | B11: Product | C11: creationtime | D11: Time created | E11: true | F11: java.util.Date | G11: Item | H11: false | J11: {Time created=} | K11: false | L11: dd.MM.yyyy HH:mm:ss
A12: {Product} | B12: Product | C12: endLineNumber | D12: Line number in XML (end) | E12: true | F12: java.lang.Integer | G12: Product | H12: false | J12: {Line number in XML (end)} | K12: false
A13: {Product} | B13: Product | C13: Europe1PriceFactory_PTG | D13: Tax Class | E13: true | F13: ProductTaxGroup | G13: Product | H13: false | J13: {Tax Class} | K13: false
A14: {Product} | B14: Product | C14: thumbnails | D14: Thumbnails | E14: true | F14: MediaCollection | G14: Product | H14: false | J14: {Thumbnails+} | K14: false | L14: filePath:code:catalog:version:folder
A15: {Product} | B15: Product | C15: packagingType | E15: true | F15: java.lang.String | G15: Product | H15: false | J15: {packagingType} | K15: false
A16: {Product} | B16: Product | C16: deliveryTime | D16: Delivery time | E16: true | F16: java.lang.Double | G16: Product | H16: false | J16: {Delivery time} | K16: false
A17: {Product} | B17: Product | C17: bucketSize | E17: true | F17: java.lang.String | G17: Product | H17: false | J17: {bucketSize} | K17: false
A18: {Product} | B18: Product | C18: sequenceId | D18: Sequence ID | E18: true | F18: java.lang.Long | G18: Product | H18: false | J18: {Sequence ID} | K18: false
A19: {Product} | B19: Product | C19: productListComponents | D19: Product List Components | E19: true | F19: ProductsForProductListComponentproductListComponentsColl | G19: Product | H19: false | J19: {Product List Components+} | K19: false | L19: ProductListComponent.uid:CatalogVersion.version:Catalog.id
A20: {Product} | B20: Product | C20: unit | D20: Sales unit | E20: true | F20: Unit | G20: Product | H20: false | J20: {Sales unit} | K20: false | L20: Unit.code
A21: {Product} | B21: Product | C21: engineMake | E21: true | F21: java.lang.String | G21: Product | H21: false | J21: {engineMake} | K21: false
A22: {Product} | B22: Product | C22: loaderReachMaxHeight | E22: true | F22: java.lang.String | G22: Product | H22: false | J22: {loaderReachMaxHeight} | K22: false
A23: {Product} | B23: Product | C23: armSize | E23: true | F23: java.lang.String | G23: Product | H23: false | J23: {armSize} | K23: false
A24: {Product} | B24: Product | C24: reviewCount | D24: Persisted Total Reviews | E24: true | F24: java.lang.Integer | G24: Product | H24: false | J24: {Persisted Total Reviews} | K24: false
A25: {Product} | B25: Product | C25: sapBlocked | D25: Blocked | E25: true | F25: java.lang.Boolean | G25: Product | H25: false | J25: {Blocked} | K25: false
A26: {Product} | B26: Product | C26: machineType | E26: true | F26: MachineType | G26: Product | H26: false | J26: {machineType} | K26: false
A27: {Product} | B27: Product | C27: materialDensity | E27: true | F27: java.lang.String | G27: Product | H27: false | J27: {materialDensity} | K27: false
A28: {Product} | B28: Product | C28: code | D28: Article Number | E28: false | F28: java.lang.String | G28: Product | H28: false | J28: {Article Number*^} | K28: true
A29: {Product} | B29: Product | C29: backhoeShovel | E29: true | F29: java.lang.String | G29: Product | H29: false | J29: {backhoeShovel} | K29: false
A30: {Product} | B30: Product | C30: sapEAN | D30: EAN | E30: true | F30: java.lang.String | G30: Product | H30: false | J30: {EAN[sapEAN]} | K30: false
A31: {Product} | B31: Product | C31: pileDensityUpto | E31: true | F31: java.lang.String | G31: Product | H31: false | J31: {pileDensityUpto} | K31: false
A32: {Product} | B32: Product | C32: ean | D32: EAN | E32: true | F32: java.lang.String | G32: Product | H32: false | J32: {EAN[ean]} | K32: false
A33: {Product} | B33: Product | C33: Europe1PriceFactory_PDG | D33: Discount Class | E33: true | F33: ProductDiscountGroup | G33: Product | H33: false | J33: {Discount Class} | K33: false
A34: {Product} | B34: Product | C34: variantType | D34: Product variants type | E34: true | F34: VariantType | G34: Product | H34: false | J34: {Product variants type} | K34: false | L34: VariantType.code
A35: {Product} | B35: Product | C35: height | E35: true | F35: java.lang.String | G35: Product | H35: false | J35: {height} | K35: false
A36: {Product} | B36: Product | C36: manufacturerTypeDescription | D36: Manufacturer description | E36: true | F36: localized:java.lang.String | G36: Product | H36: true | I36: {en},{de},{ja},{zh} | J36: {Manufacturer description[en]},{Manufacturer description[de]},{Manufacturer description[ja]},{Manufacturer description[zh]} | K36: false
A37: {Product} | B37: Product | C37: loadOverHeight | E37: true | F37: java.lang.String | G37: Product | H37: false | J37: {loadOverHeight} | K37: false
A38: {Product} | B38: Product | C38: reviewRating | D38: Persisted Average Rating | E38: true | F38: java.lang.Double | G38: Product | H38: false | J38: {Persisted Average Rating} | K38: false
A39: {Product} | B39: Product | C39: sapBaseUnitConversion | D39: Base Unit Conversion | E39: true | F39: java.lang.Double | G39: Product | H39: false | J39: {Base Unit Conversion} | K39: false
A40: {Product} | B40: Product | C40: priceQuantity | D40: Price quantity | E40: true | F40: java.lang.Double | G40: Product | H40: false | J40: {Price quantity} | K40: false
A41: {Product} | B41: Product | C41: segment | D41: Segment | E41: true | F41: localized:java.lang.String | G41: Product | H41: true | I41: {en},{de},{ja},{zh} | J41: {Segment[en]},{Segment[de]},{Segment[ja]},{Segment[zh]} | K41: false
A42: {Product} | B42: Product | C42: others | D42: Others | E42: true | F42: MediaCollection | G42: Product | H42: false | J42: {Others+} | K42: false | L42: filePath:code:catalog:version:folder
A43: {Product} | B43: Product | C43: loaderMaxDiggingDepth | E43: true | F43: java.lang.String | G43: Product | H43: false | J43: {loaderMaxDiggingDepth} | K43: false
A44: {Product} | B44: Product | C44: drive | E44: true | F44: java.lang.String | G44: Product | H44: false | J44: {drive} | K44: false
A45: {Product} | B45: Product | C45: model | E45: true | F45: java.lang.String | G45: Product | H45: false | J45: {model} | K45: false
A46: {Product} | B46: Product | C46: oilPressureRange | E46: true | F46: java.lang.String | G46: Product | H46: false | J46: {oilPressureRange} | K46: false
A47: {Product} | B47: Product | C47: productDetailComponents | D47: Product Detail Components | E47: true | F47: ProductDetailComponentsForProductproductDetailComponentsColl | G47: Product | H47: false | J47: {Product Detail Components+} | K47: false | L47: ProductDetailComponent.uid:CatalogVersion.version:Catalog.id
A48: {Product} | B48: Product | C48: loaderBucketType | E48: true | F48: java.lang.String | G48: Product | H48: false | J48: {loaderBucketType} | K48: false
A49: {Product} | B49: Product | C49: detail | D49: Details | E49: true | F49: MediaCollection | G49: Product | H49: false | J49: {Details+} | K49: false | L49: filePath:code:catalog:version:folder
A50: {Product} | B50: Product | C50: tyre | E50: true | F50: java.lang.String | G50: Product | H50: false | J50: {tyre} | K50: false
A51: {Product} | B51: Product | C51: maxDiggingDepth | E51: true | F51: java.lang.String | G51: Product | H51: false | J51: {maxDiggingDepth} | K51: false
A52: {Product} | B52: Product | C52: productCarouselComponents | D52: Carousel Components | E52: true | F52: ProductsForProductCarouselComponentproductCarouselComponentsColl | G52: Product | H52: false | J52: {Carousel Components+} | K52: false | L52: ProductCarouselComponent.uid:CatalogVersion.version:Catalog.id
A53: {Product} | B53: Product | C53: picture | D53: Image | E53: true | F53: Media | G53: Product | H53: false | J53: {Image} | K53: false | L53: filePath:code:catalog:version:folder
A54: {Product} | B54: Product | C54: application | E54: true | F54: java.lang.String | G54: Product | H54: false | J54: {application} | K54: false
A55: {Product} | B55: Product | C55: sapBlockedDate | D55: Blocked Date | E55: true | F55: java.util.Date | G55: Product | H55: false | J55: {Blocked Date} | K55: false | L55: dd.MM.yyyy HH:mm:ss
A56: {Product} | B56: Product | C56: applicableModel | E56: true | F56: java.lang.String | G56: Product | H56: false | J56: {applicableModel} | K56: false
A57: {Product} | B57: Product | C57: contractPeriod | E57: true | F57: java.lang.String | G57: Product | H57: false | J57: {contractPeriod} | K57: false
A58: {Product} | B58: Product | C58: bucketType | E58: true | F58: java.lang.String | G58: Product | H58: false | J58: {bucketType} | K58: false
A59: {Product} | B59: Product | C59: telematics | E59: true | F59: java.lang.String | G59: Product | H59: false | J59: {telematics} | K59: false
A60: {Product} | B60: Product | C60: hsn | E60: true | F60: java.lang.String | G60: Product | H60: false | J60: {hsn} | K60: false
A61: {Product} | B61: Product | C61: engineModel | E61: true | F61: java.lang.String | G61: Product | H61: false | J61: {engineModel} | K61: false
A62: {Product} | B62: Product | C62: numberContentUnits | D62: Package quantity | E62: true | F62: java.lang.Double | G62: Product | H62: false | J62: {Package quantity} | K62: false
A63: {Product} | B63: Product | C63: orderQuantityInterval | D63: Order quantity interval | E63: true | F63: java.lang.Integer | G63: Product | H63: false | J63: {Order quantity interval} | K63: false
A64: {Product} | B64: Product | C64: subHeader | E64: true | F64: java.lang.String | G64: Product | H64: false | J64: {subHeader} | K64: false
A65: {Product} | B65: Product | C65: supercategories | D65: Supercategories | E65: true | F65: CategoryProductRelationsupercategoriesColl | G65: Product | H65: false | J65: {Supercategories+} | K65: false | L65: Category.code:CatalogVersion.version:Catalog.id
A66: {Product} | B66: Product | C66: supplierAlternativeAID | D66: Alternative ID | E66: true | F66: java.lang.String | G66: Product | H66: false | J66: {Alternative ID} | K66: false
A67: {Product} | B67: Product | C67: manufacturerName | D67: Manufacturer | E67: true | F67: java.lang.String | G67: Product | H67: false | J67: {Manufacturer} | K67: false
A68: {Product} | B68: Product | C68: nomenclature | E68: true | F68: java.lang.String | G68: Product | H68: false | J68: {nomenclature} | K68: false
A69: {Product} | B69: Product | C69: noOfVisits | E69: true | F69: java.lang.String | G69: Product | H69: false | J69: {noOfVisits} | K69: false
A70: {Product} | B70: Product | C70: europe1Prices | D70: Prices | E70: true | F70: PriceRowCollectionType | G70: Product | H70: false | J70: {Prices+} | K70: false | L70: price currency:N|G:user|userPriceGroup:minQuantity unit:[dd.MM.yyyy HH:mm:ss to dd.MM.yyyy HH:mm:ss]:channel
A71: {Product} | B71: Product | C71: Europe1PriceFactory_PPG | D71: Price Class | E71: true | F71: ProductPriceGroup | G71: Product | H71: false | J71: {Price Class} | K71: false
A72: {Product} | B72: Product | C72: pipingKit | E72: true | F72: java.lang.String | G72: Product | H72: false | J72: {pipingKit} | K72: false
A73: {Product} | B73: Product | C73: xmlcontent | D73: XML fragment | E73: true | F73: java.lang.String | G73: Product | H73: false | J73: {XML fragment} | K73: false
A74: {Product} | B74: Product | C74: catalogVersion | D74: Catalog version | E74: false | F74: CatalogVersion | G74: Product | H74: false | J74: {Catalog version*^} | K74: true | L74: CatalogVersion.version:Catalog.id
A75: {Product} | B75: Product | C75: ownEurope1Prices | D75: Own Price Rows | E75: true | F75: Product2OwnEurope1PricesownEurope1PricesColl | G75: Product | H75: false | J75: {Own Price Rows+} | K75: false | L75: price currency:N|G:user|userPriceGroup:minQuantity unit:[dd.MM.yyyy HH:mm:ss to dd.MM.yyyy HH:mm:ss]:channel
A76: {Product} | B76: Product | C76: erpGroupBuyer | D76: ERP group buyer | E76: true | F76: java.lang.String | G76: Product | H76: false | J76: {ERP group buyer} | K76: false
A77: {Product} | B77: Product | C77: modifiedtime | D77: Time modified | E77: true | F77: java.util.Date | G77: Item | H77: false | J77: {Time modified} | K77: false | L77: dd.MM.yyyy HH:mm:ss
A78: {Product} | B78: Product | C78: soldIndividually | D78: Sold individually | E78: true | F78: java.lang.Boolean | G78: Product | H78: false | J78: {Sold individually} | K78: false
A79: {Product} | B79: Product | C79: onlineDate | D79: Online from | E79: true | F79: java.util.Date | G79: Product | H79: false | J79: {Online from} | K79: false | L79: dd.MM.yyyy HH:mm:ss
A80: {Product} | B80: Product | C80: maxReach | E80: true | F80: java.lang.String | G80: Product | H80: false | J80: {maxReach} | K80: false
A81: {Product} | B81: Product | C81: minOrderQuantity | D81: Min order quantity | E81: true | F81: java.lang.Integer | G81: Product | H81: false | J81: {Min order quantity} | K81: false
A82: {Product} | B82: Product | C82: customProductName | E82: true | F82: java.lang.String | G82: Product | H82: false | J82: {customProductName} | K82: false
A83: {Product} | B83: Product | C83: relatedPart | E83: true | F83: java.lang.String | G83: Product | H83: false | J83: {relatedPart} | K83: false
A84: {Product} | B84: Product | C84: machinePriceClass | E84: true | F84: java.lang.String | G84: Product | H84: false | J84: {machinePriceClass} | K84: false
A85: {Product} | B85: Product | C85: loaderDumpingHeight | E85: true | F85: java.lang.String | G85: Product | H85: false | J85: {loaderDumpingHeight} | K85: false
A86: {Product} | B86: Product | C86: mcBuild | E86: true | F86: java.lang.String | G86: Product | H86: false | J86: {mcBuild} | K86: false
A87: {Product} | B87: Product | C87: location | E87: true | F87: java.lang.String | G87: Product | H87: false | J87: {location} | K87: false
A88: {Product} | B88: Product | C88: make | E88: true | F88: java.lang.String | G88: Product | H88: false | J88: {make} | K88: false
A89: {Product} | B89: Product | C89: simpleResponsiveBannerComponents | D89: Simple Responsive Banner Components | E89: true | F89: SimpleResponsiveBannerComponentsForProductsimpleResponsiveBannerComponentsColl | G89: Product | H89: false | J89: {Simple Responsive Banner Components+} | K89: false | L89: SimpleResponsiveBannerComponent.uid:CatalogVersion.version:Catalog.id
A90: {Product} | B90: Product | C90: boomSize | E90: true | F90: java.lang.String | G90: Product | H90: false | J90: {boomSize} | K90: false
A91: {Product} | B91: Product | C91: data_sheet | D91: Specifications | E91: true | F91: MediaCollection | G91: Product | H91: false | J91: {Specifications+} | K91: false | L91: filePath:code:catalog:version:folder
A92: {Product} | B92: Product | C92: weight | E92: true | F92: java.lang.String | G92: Product | H92: false | J92: {weight} | K92: false
A93: {Product} | B93: Product | C93: contractPdf | E93: true | F93: Media | G93: Product | H93: false | J93: {contractPdf} | K93: false | L93: filePath:code:catalog:version:folder
A94: {Product} | B94: Product | C94: cuttingHeight | E94: true | F94: java.lang.String | G94: Product | H94: false | J94: {cuttingHeight} | K94: false
A95: {Product} | B95: Product | C95: speciality | E95: true | F95: java.lang.String | G95: Product | H95: false | J95: {speciality} | K95: false
A96: {Product} | B96: Product | C96: duration | E96: true | F96: java.lang.String | G96: Product | H96: false | J96: {duration} | K96: false
A97: {Product} | B97: Product | C97: shoeWidthmm | E97: true | F97: java.lang.String | G97: Product | H97: false | J97: {shoeWidthmm} | K97: false
A98: {Product} | B98: Product | C98: restrictions | D98: Restrictions | E98: true | F98: ProductsForRestrictionrestrictionsColl | G98: Product | H98: false | J98: {Restrictions+} | K98: false | L98: CMSProductRestriction.uid:CatalogVersion.version:Catalog.id
A99: {Product} | B99: Product | C99: galleryImages | D99: Gallery Images | E99: true | F99: MediaContainerList | G99: Product | H99: false | J99: {Gallery Images+} | K99: false | L99: MediaContainer.qualifier:CatalogVersion.version:Catalog.id
A100: {Product} | B100: Product | C100: chiselDiameter | E100: true | F100: java.lang.String | G100: Product | H100: false | J100: {chiselDiameter} | K100: false
...

Sheet ClassificationTypeSystem
A1: FullName | B1: ClassificationSystem | C1: ClassificationVersion | D1: ClassificationClass | E1: ClassificationAttribute | F1: AttrLocalized | G1: AttrLocLang | H1: IsMandatory

Sheet HeaderPrompt
A1: HeaderTypeCode | B1: HeaderAttrDisplayedName | C1: HeaderReferenceFormat
A2: Product | B2: Alternative ID
A3: Product | B3: Approval
A4: Product | B4: Article Number*^
A5: Product | B5: Article order
A6: Product | B6: Base Unit Conversion
A7: Product | B7: Blocked
A8: Product | B8: Blocked Date | C8: dd.MM.yyyy HH:mm:ss
A9: Product | B9: Carousel Components+ | C9: ProductCarouselComponent.uid:CatalogVersion.version:Catalog.id
A10: Product | B10: Catalog version*^ | C10: CatalogVersion.version:Catalog.id
A11: Product | B11: Comments+ | C11: Comment.code
A12: Product | B12: Configurable
A13: Product | B13: Content unit | C13: Unit.code
A14: Product | B14: Delivery Modes+ | C14: DeliveryMode.code
A15: Product | B15: Delivery time
A16: Product | B16: Description[zh]
A17: Product | B17: Description[de]
A18: Product | B18: Description[ja]
A19: Product | B19: Description[en]
A20: Product | B20: Details+ | C20: filePath:code:catalog:version:folder
A21: Product | B21: Discount Class
A22: Product | B22: EAN[sapEAN]
A23: Product | B23: EAN[ean]
A24: Product | B24: ERP group buyer
A25: Product | B25: ERP group supplier
A26: Product | B26: Gallery Images+ | C26: MediaContainer.qualifier:CatalogVersion.version:Catalog.id
A27: Product | B27: Identifier[de]
A28: Product | B28: Identifier[ja]
A29: Product | B29: Identifier[en]
A30: Product | B30: Identifier[zh]
A31: Product | B31: Image | C31: filePath:code:catalog:version:folder
A32: Product | B32: Keywords[de]+ | C32: Keyword.keyword:CatalogVersion.version:Catalog.id:Language.isocode
A33: Product | B33: Keywords[zh]+ | C33: Keyword.keyword:CatalogVersion.version:Catalog.id:Language.isocode
A34: Product | B34: Keywords[en]+ | C34: Keyword.keyword:CatalogVersion.version:Catalog.id:Language.isocode
A35: Product | B35: Keywords[ja]+ | C35: Keyword.keyword:CatalogVersion.version:Catalog.id:Language.isocode
A36: Product | B36: Line number in XML (end)
A37: Product | B37: Line number in XML (start)
A38: Product | B38: Link Components+ | C38: CMSLinkComponent.uid:CatalogVersion.version:Catalog.id
A39: Product | B39: Logos+ | C39: filePath:code:catalog:version:folder
A40: Product | B40: Manufacturer
A41: Product | B41: Manufacturer AID
A42: Product | B42: Manufacturer description[en]
A43: Product | B43: Manufacturer description[zh]
A44: Product | B44: Manufacturer description[ja]
A45: Product | B45: Manufacturer description[de]
A46: Product | B46: Max order quantity
A47: Product | B47: Min order quantity
A48: Product | B48: Normals+ | C48: filePath:code:catalog:version:folder
A49: Product | B49: Online from | C49: dd.MM.yyyy HH:mm:ss
A50: Product | B50: Online to | C50: dd.MM.yyyy HH:mm:ss
A51: Product | B51: Order quantity interval
A52: Product | B52: Others+ | C52: filePath:code:catalog:version:folder
A53: Product | B53: Own Price Rows+ | C53: price currency:N|G:user|userPriceGroup:minQuantity unit:[dd.MM.yyyy HH:mm:ss to dd.MM.yyyy HH:mm:ss]:channel
A54: Product | B54: Package quantity
A55: Product | B55: Persisted Average Rating
A56: Product | B56: Persisted Total Reviews
A57: Product | B57: Price Class
A58: Product | B58: Price quantity
A59: Product | B59: Prices+ | C59: price currency:N|G:user|userPriceGroup:minQuantity unit:[dd.MM.yyyy HH:mm:ss to dd.MM.yyyy HH:mm:ss]:channel
A60: Product | B60: Product Detail Components+ | C60: ProductDetailComponent.uid:CatalogVersion.version:Catalog.id
A61: Product | B61: Product Feature Components+ | C61: ProductFeatureComponent.uid:CatalogVersion.version:Catalog.id
A62: Product | B62: Product List Components+ | C62: ProductListComponent.uid:CatalogVersion.version:Catalog.id
A63: Product | B63: Product variants type | C63: VariantType.code
A64: Product | B64: Remarks[zh]
A65: Product | B65: Remarks[ja]
A66: Product | B66: Remarks[de]
A67: Product | B67: Remarks[en]
A68: Product | B68: Restrictions+ | C68: CMSProductRestriction.uid:CatalogVersion.version:Catalog.id
A69: Product | B69: Sales unit | C69: Unit.code
A70: Product | B70: Segment[ja]
A71: Product | B71: Segment[zh]
A72: Product | B72: Segment[de]
A73: Product | B73: Segment[en]
A74: Product | B74: Sequence ID
A75: Product | B75: Simple Banner Components+ | C75: SimpleBannerComponent.uid:CatalogVersion.version:Catalog.id
A76: Product | B76: Simple Responsive Banner Components+ | C76: SimpleResponsiveBannerComponent.uid:CatalogVersion.version:Catalog.id
A77: Product | B77: Sold individually
A78: Product | B78: Specifications+ | C78: filePath:code:catalog:version:folder
A79: Product | B79: Summary[de]
A80: Product | B80: Summary[zh]
A81: Product | B81: Summary[ja]
A82: Product | B82: Summary[en]
A83: Product | B83: Supercategories+ | C83: Category.code:CatalogVersion.version:Catalog.id
A84: Product | B84: Tax Class
A85: Product | B85: Thumbnail | C85: filePath:code:catalog:version:folder
A86: Product | B86: Thumbnails+ | C86: filePath:code:catalog:version:folder
A87: Product | B87: Time created= | C87: dd.MM.yyyy HH:mm:ss
A88: Product | B88: Time modified | C88: dd.MM.yyyy HH:mm:ss
A89: Product | B89: Video Components+ | C89: VideoComponent.uid:CatalogVersion.version:Catalog.id
A90: Product | B90: XML fragment
A91: Product | B91: airConditionedCab
A92: Product | B92: applicableModel
A93: Product | B93: application
A94: Product | B94: armSize
A95: Product | B95: backhoeShovel
A96: Product | B96: boomSize
A97: Product | B97: bucketSize
A98: Product | B98: bucketType
A99: Product | B99: chiselDiameter
A100: Product | B100: contractPdf | C100: filePath:code:catalog:version:folder
...

Sheet products
A1: Article Number | B1: Description | C1: Identifier | D1: Keywords | E1: Price | F1: Price quantity | G1: Prices+ | H1: Sold individually | I1: height | J1: length | K1: operatingWeight | L1: productType | M1: weight | N1: width
A2: YD40000702 | C2: COVER | E2: 0.0 INR:N::1 EA:: | F2: 1.0 | G2: 0.0 INR:N::1 EA:: | H2: true | L2: SpareParts
A3: YD00008723 | C3: SEAL;RUBBER | F3: 1.0 | H3: true | L3: SpareParts
A4: YD00004167 | C4: * ROLLER | F4: 1.0 | H4: true | L4: SpareParts
A5: YD00001375 | C5: BUSHING;RUBBER | F5: 1.0 | H5: true | L5: SpareParts
A6: YD00010097 | C6: INSULATOR | F6: 1.0 | H6: true | L6: SpareParts
A7: YD00003341 | C7: HOSE | F7: 1.0 | H7: true | L7: SpareParts
A8: YD00000772 | C8: HOSE | E8: 5235.66 INR:N::1 EA:: | F8: 1.0 | G8: 5235.66 INR:N::1 EA:: | H8: true | L8: SpareParts
A9: YD00002131 | C9: SEAL;RUBBER | F9: 1.0 | H9: true | L9: SpareParts
A10: YD00011148 | C10: INSULATOR | F10: 1.0 | H10: true | L10: SpareParts
A11: YD00006406 | C11: PLATE | F11: 1.0 | H11: true | L11: SpareParts
A12: YD40002054 | C12: PIPE | E12: 4761.3 INR:N::1 EA:: | F12: 1.0 | G12: 4761.3 INR:N::1 EA:: | H12: true | L12: SpareParts
A13: YD00008711 | C13: SEAL;RUBBER | E13: 1667.34 INR:N::1 EA:: | F13: 1.0 | G13: 1667.34 INR:N::1 EA:: | H13: true | L13: SpareParts
A14: YD00003427 | C14: BRACKET | F14: 1.0 | H14: true | L14: SpareParts
A15: YD00007645 | C15: NAME-PLATE | E15: 743.4 INR:N::1 EA:: | F15: 1.0 | G15: 743.4 INR:N::1 EA:: | H15: true | L15: SpareParts
A16: YD00005399 | C16: COVER | F16: 1.0 | H16: true | L16: SpareParts
A17: YD00003282 | C17: HOSE | E17: 4089.88 INR:N::1 EA:: | F17: 1.0 | G17: 4089.88 INR:N::1 EA:: | H17: true | L17: SpareParts
A18: YD60003392 | C18: PLATE | E18: 0.0 INR:N::1 EA:: | F18: 1.0 | G18: 0.0 INR:N::1 EA:: | H18: true | L18: SpareParts
A19: YD00005162 | B19: Engine Fan Belt | C19: BELT FAN | E19: 4030.88 INR:N::1 EA:: | F19: 1.0 | G19: 4030.88 INR:N::1 EA:: | H19: true | K19: 1 | L19: SpareParts
A20: YD00001182 | C20: SEAL;RUBBER | F20: 1.0 | H20: true | L20: SpareParts
A21: YD40002594 | C21: STOPPER | F21: 1.0 | H21: true | L21: SpareParts
A22: YD00004027 | C22: *HOSE | F22: 1.0 | H22: true | L22: SpareParts
A23: YD40000549 | C23: BRACKET | F23: 1.0 | H23: true | L23: SpareParts
A24: YD00008868 | C24: * SECTION (BOOM) | E24: 89604.48 INR:N::1 EA:: | F24: 1.0 | G24: 89604.48 INR:N::1 EA:: | H24: true | L24: SpareParts
A25: YD00003278 | C25: BRACKET | F25: 1.0 | H25: true | L25: SpareParts
A26: YD00003088 | C26: SEAL;RUBBER | F26: 1.0 | H26: true | L26: SpareParts
A27: YD00006007 | C27: HOSE;COOLER | E27: 0.0 INR:N::1 EA:: | F27: 1.0 | G27: 0.0 INR:N::1 EA:: | H27: true | L27: SpareParts
A28: YD00007887 | B28: B30_Attachment | C28: VALVE | E28: 7232.22 INR:N::1 EA:: | F28: 1.0 | G28: 7232.22 INR:N::1 EA:: | H28: true | I28: 81 | J28: 81 | K28: 1 | L28: SpareParts | M28: 1.00 | N28: 36
A29: YD00008053 | C29: INSULATOR | F29: 1.0 | H29: true | L29: SpareParts
A30: YD00008883 | B30: Applicable Cylinder Part No YD00006748 | C30: BOOM CYLINDER SEAL KIT | E30: 21074.8 INR:N::1 EA:: | F30: 1.0 | G30: 21074.8 INR:N::1 EA:: | H30: true | I30: 150 | J30: 150 | K30: 1 | L30: SpareParts | M30: 0.20 | N30: 40
A31: YD00007975 | C31: * LINK | E31: 0.0 INR:N::1 EA:: | F31: 1.0 | G31: 0.0 INR:N::1 EA:: | H31: true | L31: SpareParts
A32: YD60003622 | C32: ASSY;HOSE | E32: 2017.8 INR:N::1 EA:: | F32: 1.0 | G32: 2017.8 INR:N::1 EA:: | H32: true | L32: SpareParts
A33: YD00004592 | C33: HOSE | F33: 1.0 | H33: true | L33: SpareParts
A34: YD00000877 | C34: COVER;REAR | E34: 20816.38 INR:N::1 EA:: | F34: 1.0 | G34: 20816.38 INR:N::1 EA:: | H34: true | L34: SpareParts
A35: YD60005326 | C35: ASSY;HOSE | E35: 2456.76 INR:N::1 EA:: | F35: 1.0 | G35: 2456.76 INR:N::1 EA:: | H35: true | L35: SpareParts
A36: YD00000517 | C36: * SECTION (BLADE) | F36: 1.0 | H36: true | L36: SpareParts
A37: YD00005513 | C37: NUT | F37: 1.0 | H37: true | L37: SpareParts
A38: YD00002130 | C38: SEAL;RUBBER | F38: 1.0 | H38: true | L38: SpareParts
A39: YD40001465 | C39: BRACKET | E39: 1877.38 INR:N::1 EA:: | F39: 1.0 | G39: 1877.38 INR:N::1 EA:: | H39: true | L39: SpareParts
A40: YD40000371 | C40: FRAME;MAIN | E40: 1280275.22 INR:N::1 EA:: | F40: 1.0 | G40: 1280275.22 INR:N::1 EA:: | H40: true | L40: SpareParts
A41: YD00006950 | C41: MUFFLER | E41: 57776.64 INR:N::1 EA:: | F41: 1.0 | G41: 57776.64 INR:N::1 EA:: | H41: true | L41: SpareParts
A42: YD00000979 | B42: Radiator Bottom Hose | C42: HOSE _WATER | E42: 2932.0 INR:N::1 EA:: | F42: 1.0 | G42: 2932.0 INR:N::1 EA:: | H42: true | I42: 640 | J42: 640 | K42: 1 | L42: SpareParts | M42: 0.50 | N42: 6
A43: YD60002323 | C43: PARTS;SWING | F43: 1.0 | H43: true | L43: SpareParts
A44: YD40001183 | C44: COVER | E44: 68888.4 INR:N::1 EA:: | F44: 1.0 | G44: 68888.4 INR:N::1 EA:: | H44: true | L44: SpareParts
A45: YD00006328 | C45: NAME-PLATE | E45: 0.0 INR:N::1 EA:: | F45: 1.0 | G45: 0.0 INR:N::1 EA:: | H45: true | L45: SpareParts
A46: YD00005366 | C46: WASHER | F46: 1.0 | H46: true | L46: SpareParts
A47: YD00002073 | C47: COVER | E47: 0.0 INR:N::1 EA:: | F47: 1.0 | G47: 0.0 INR:N::1 EA:: | H47: true | L47: SpareParts
A48: YD00004424 | C48: GEAR;PLANETARY | E48: 6288.22 INR:N::1 EA:: | F48: 1.0 | G48: 6288.22 INR:N::1 EA:: | H48: true | L48: SpareParts
A49: YD00010121 | C49: INSULATOR | E49: 0.0 INR:N::1 EA:: | F49: 1.0 | G49: 0.0 INR:N::1 EA:: | H49: true | L49: SpareParts
A50: YD00006479 | C50: SEAL;RUBBER | E50: 0.0 INR:N::1 EA:: | F50: 1.0 | G50: 0.0 INR:N::1 EA:: | H50: true | L50: SpareParts
A51: YD00003161 | C51: FILTER;FUEL | E51: 8035.8 INR:N::1 EA:: | F51: 1.0 | G51: 8035.8 INR:N::1 EA:: | H51: true | L51: SpareParts
A52: YD60005287 | C52: ASSY;HOSE (LABEL;6A) | E52: 0.0 INR:N::1 EA:: | F52: 1.0 | G52: 0.0 INR:N::1 EA:: | H52: true | L52: SpareParts
A53: YD00004654 | C53: SEAL;RUBBER | F53: 1.0 | H53: true | L53: SpareParts
A54: YD00005379 | C54: RUBBER;CUSHION | F54: 1.0 | H54: true | L54: SpareParts
A55: YD40000118 | C55: * CANOPY;ROPS | E55: 207085.28 INR:N::1 EA:: | F55: 1.0 | G55: 207085.28 INR:N::1 EA:: | H55: true | L55: SpareParts
A56: YD00003337 | C56: HOSE | F56: 1.0 | H56: true | L56: SpareParts
A57: YD00000849 | C57: BUSHING | E57: 5399.68 INR:N::1 EA:: | F57: 1.0 | G57: 5399.68 INR:N::1 EA:: | H57: true | L57: SpareParts
A58: YD40000416 | C58: BRACKET | F58: 1.0 | H58: true | L58: SpareParts
A59: YD60002756 | C59: ASSY;HOSE | F59: 1.0 | H59: true | L59: SpareParts
A60: YD00001169 | C60: SEAL;RUBBER | F60: 1.0 | H60: true | L60: SpareParts
A61: YD00007438 | C61: SEAL;RUBBER | F61: 1.0 | H61: true | L61: SpareParts
A62: YD60003290 | C62: ASSY;HOSE | E62: 4070.0 INR:N::1 EA:: | F62: 1.0 | G62: 4070.0 INR:N::1 EA:: | H62: true | L62: SpareParts
A63: YD40004863 | C63: COVER;FRONT | E63: 62698.12 INR:N::1 EA:: | F63: 1.0 | G63: 62698.12 INR:N::1 EA:: | H63: true | L63: SpareParts
A64: YD60003317 | C64: ASSY;HOSE | E64: 1250.8 INR:N::1 EA:: | F64: 1.0 | G64: 1250.8 INR:N::1 EA:: | H64: true | L64: SpareParts
A65: YD00000461 | C65: RUBBER | E65: 0.0 INR:N::1 EA:: | F65: 1.0 | G65: 0.0 INR:N::1 EA:: | H65: true | L65: SpareParts
A66: YD00000369 | C66: CYL.;SWING | E66: 207584.42 INR:N::1 EA:: | F66: 1.0 | G66: 207584.42 INR:N::1 EA:: | H66: true | L66: SpareParts
A67: YD00001647 | C67: COLLAR | E67: 0.0 INR:N::1 EA:: | F67: 1.0 | G67: 0.0 INR:N::1 EA:: | H67: true | L67: SpareParts
A68: YD00000013 | C68: HARNESS;WIRE | F68: 1.0 | H68: true | L68: SpareParts
A69: YD60003311 | C69: ASSY;HOSE | F69: 1.0 | H69: true | L69: SpareParts
A70: YD40000368 | C70: * FRAME;TRACK | F70: 1.0 | H70: true | L70: SpareParts
A71: YD00001196 | C71: SEAL;RUBBER | F71: 1.0 | H71: true | L71: SpareParts
A72: YD00000830 | C72: RUBBER | E72: 0.0 INR:N::1 EA:: | F72: 1.0 | G72: 0.0 INR:N::1 EA:: | H72: true | L72: SpareParts
A73: YD00003353 | C73: HOSE | E73: 3316.98 INR:N::1 EA:: | F73: 1.0 | G73: 3316.98 INR:N::1 EA:: | H73: true | L73: SpareParts
A74: YD00012504 | C74: CYL;BLADE | F74: 1.0 | H74: true | L74: SpareParts
A75: YD60005281 | C75: ASSY;HOSE | E75: 1323.96 INR:N::1 EA:: | F75: 1.0 | G75: 1323.96 INR:N::1 EA:: | H75: true | L75: SpareParts
A76: YD00000365 | B76: BOOM CYLINDER Assy | C76: CYL.BOOM | E76: 102496.0 INR:N::1 EA:: | F76: 1.0 | G76: 102496.0 INR:N::1 EA:: | H76: true | K76: 1 | L76: SpareParts | M76: 34.40
A77: YD40002438 | C77: PLATE | E77: 0.0 INR:N::1 EA:: | F77: 1.0 | G77: 0.0 INR:N::1 EA:: | H77: true | L77: SpareParts
A78: YD00005810 | C78: * INDICATOR | E78: 3917.6 INR:N::1 EA:: | F78: 1.0 | G78: 3917.6 INR:N::1 EA:: | H78: true | L78: SpareParts
A79: YD00004956 | C79: * SASH | F79: 1.0 | H79: true | L79: SpareParts
A80: YD40002521 | C80: BRACKET | E80: 0.0 INR:N::1 EA:: | F80: 1.0 | G80: 0.0 INR:N::1 EA:: | H80: true | L80: SpareParts
A81: YD60003331 | C81: ASSY;HOSE | E81: 312.7 INR:N::1 EA:: | F81: 1.0 | G81: 312.7 INR:N::1 EA:: | H81: true | L81: SpareParts
A82: YD40000554 | C82: BRACKET | F82: 1.0 | H82: true | L82: SpareParts
A83: YD60000785 | C83: PUMP;PISTON | F83: 1.0 | H83: true | L83: SpareParts
A84: YD00003551 | C84: VALVE;SOLENOID | E84: 31110.7 INR:N::1 EA:: | F84: 1.0 | G84: 31110.7 INR:N::1 EA:: | H84: true | L84: SpareParts
A85: YD40000465 | C85: BRACKET | F85: 1.0 | H85: true | L85: SpareParts
A86: YD00005386 | C86: * PLATE | F86: 1.0 | H86: true | L86: SpareParts
A87: YD00003112 | C87: INSULATOR | F87: 1.0 | H87: true | L87: SpareParts
A88: YD60001427 | C88: ELECTRIC-PART | F88: 1.0 | H88: true | L88: SpareParts
A89: YD00002910 | C89: HARNESS;WIRE | E89: 0.0 INR:N::1 EA:: | F89: 1.0 | G89: 0.0 INR:N::1 EA:: | H89: true | L89: SpareParts
A90: YD40000350 | C90: CATCH | F90: 1.0 | H90: true | L90: SpareParts
A91: YD00003695 | C91: SEAL;RUBBER | F91: 1.0 | H91: true | L91: SpareParts
A92: YD00002459 | C92: SEAL;RUBBER | F92: 1.0 | H92: true | L92: SpareParts
A93: YD00003362 | C93: HOSE | E93: 7379.72 INR:N::1 EA:: | F93: 1.0 | G93: 7379.72 INR:N::1 EA:: | H93: true | L93: SpareParts
A94: YD00003355 | C94: HOSE | E94: 4041.5 INR:N::1 EA:: | F94: 1.0 | G94: 4041.5 INR:N::1 EA:: | H94: true | L94: SpareParts
A95: YD40002052 | C95: PIPE | E95: 3109.3 INR:N::1 EA:: | F95: 1.0 | G95: 3109.3 INR:N::1 EA:: | H95: true | L95: SpareParts
A96: YD00003354 | C96: HOSE | E96: 3516.4 INR:N::1 EA:: | F96: 1.0 | G96: 3516.4 INR:N::1 EA:: | H96: true | L96: SpareParts
A97: YD00002122 | C97: SEAL;RUBBER | F97: 1.0 | H97: true | L97: SpareParts
A98: YD40001836 | C98: WEIGHT;COUNTER(363kg) | E98: 249207.74 INR:N::1 EA:: | F98: 1.0 | G98: 249207.74 INR:N::1 EA:: | H98: true | L98: SpareParts
A99: YD00012085 | C99: VALVE;SOLENOID | E99: 40437.42 INR:N::1 EA:: | F99: 1.0 | G99: 40437.42 INR:N::1 EA:: | H99: true | L99: SpareParts
A100: YD60002676 | C100: ASSY;HOSE | F100: 1.0 | H100: true | L100: SpareParts
...
